bgen_reader/__init__.py
bgen_reader/_bgen2.py
bgen_reader/_dosage.py
bgen_reader/_environment.py
bgen_reader/_example.py
bgen_reader/_file.py
bgen_reader/_genotype.py
bgen_reader/_helper.py
bgen_reader/_metafile.py
bgen_reader/_multimemmap.py
bgen_reader/_reader.py
bgen_reader/_samples.py
bgen_reader/_testit.py
bgen_reader/conftest.py
bgen_reader/test/__init__.py
bgen_reader/test/test_bgen2.py
bgen_reader/test/test_bgen_reader.py
bgen_reader/test/test_dosage.py
bgen_reader/test/test_dosage2.py
bgen_reader/test/test_interface.py
bgen_reader/test/test_large_file.py
bgen_reader/test/test_multimemmap.py
bgen_reader/test/write_random.py
bgen_reader-4.0.9.dist-info/LICENSE.md
bgen_reader-4.0.9.dist-info/METADATA
bgen_reader-4.0.9.dist-info/WHEEL
bgen_reader-4.0.9.dist-info/RECORD
