Metadata-Version: 2.1
Name: bgen-reader
Version: 4.0.9
Summary: Bgen file format reader
License: MIT
Author: Danilo Horta
Author-email: horta@ebi.ac.uk
Requires-Python: >=3.10,<4.0
Classifier: License :: OSI Approved :: MIT License
Classifier: Programming Language :: Python :: 3
Classifier: Programming Language :: Python :: 3.10
Classifier: Programming Language :: Python :: 3.11
Classifier: Programming Language :: Python :: 3.12
Classifier: Programming Language :: Python :: 3.13
Provides-Extra: docs
Requires-Dist: appdirs (>=1.4.4,<2.0.0)
Requires-Dist: cachetools (>=5.5.0,<6.0.0)
Requires-Dist: cbgen (>=1.0.6,<2.0.0)
Requires-Dist: dask[array,bag,dataframe,delayed] (>=2024.10.0,<2025.0.0)
Requires-Dist: limix-sphinx-theme (>=0.0.4,<0.0.5) ; extra == "docs"
Requires-Dist: numpy (>=2.1.2,<3.0.0)
Requires-Dist: pandas (>=2.2.3,<3.0.0)
Requires-Dist: requests (>=2.32.3,<3.0.0)
Requires-Dist: sphinx (>=8.1.3,<9.0.0) ; extra == "docs"
Requires-Dist: sphinx-rtd-theme (>=3.0.1,<4.0.0) ; extra == "docs"
Requires-Dist: texttable (>=1.7.0,<2.0.0)
Requires-Dist: tqdm (>=4.66.5,<5.0.0)
Requires-Dist: xarray (>=2024.10.0,<2025.0.0)
